km3learn/__init__.py
km3learn/cut.py
km3learn/data.py
km3learn/features.py
km3learn/hits.py
km3learn/label.py
km3learn/metrics.py
km3learn/plot.py
km3learn/process.py
km3learn-0.1.0.dist-info/DESCRIPTION.rst
km3learn-0.1.0.dist-info/METADATA
km3learn-0.1.0.dist-info/RECORD
km3learn-0.1.0.dist-info/WHEEL
km3learn-0.1.0.dist-info/metadata.json
km3learn-0.1.0.dist-info/top_level.txt
