Metadata-Version: 2.0
Name: km3learn
Version: 0.1.0
Summary: Machine Learning
Home-page: http://git.km3net.de/km3learn/km3learn
Author: Moritz Lotze
Author-email: mlotze@km3net.de
License: BSD-3
Platform: UNKNOWN
Requires-Dist: matplotlib (>=2)
Requires-Dist: numpy
Requires-Dist: pandas
Requires-Dist: scikit-learn
